hexdi/__init__.py
hexdi/core.py
hexdi/decorator.py
hexdi/finder.py
hexdi/gentype.py
hexdi/lifetime.py
hexdi/loader.py
hexdi/meta.py
hexdi/utils.py
hexdi-0.2.2.dist-info/LICENSE
hexdi-0.2.2.dist-info/METADATA
hexdi-0.2.2.dist-info/WHEEL
hexdi-0.2.2.dist-info/top_level.txt
hexdi-0.2.2.dist-info/RECORD
