Metadata-Version: 2.1
Name: hexdi
Version: 0.2.2
Summary: Highly extensible Dependency injection framework for humans
Home-page: https://github.com/zibertscrem/hexdi
Author: Dmitriy Selischev
Author-email: zibertscrem@gmail.com
License: MIT
Platform: UNKNOWN
Classifier: Development Status :: 5 - Production/Stable
Classifier: Intended Audience :: Developers
Classifier: Topic :: Software Development :: Libraries :: Application Frameworks
Classifier: License :: OSI Approved :: MIT License
Classifier: Programming Language :: Python :: 3.5
Classifier: Programming Language :: Python :: 3.6
Classifier: Programming Language :: Python :: 3.7
Classifier: Programming Language :: Python :: 3.8
Classifier: Programming Language :: Python :: 3.9
Classifier: Programming Language :: Python :: 3.10
Requires-Python: >=3.5,<4
License-File: LICENSE
